pretty_logger/__init__.py
pretty_logger/py.typed
py_pretty_logger-2.1.0.dist-info/LICENSE
py_pretty_logger-2.1.0.dist-info/METADATA
py_pretty_logger-2.1.0.dist-info/WHEEL
py_pretty_logger-2.1.0.dist-info/top_level.txt
py_pretty_logger-2.1.0.dist-info/RECORD
